AUTHORS
LICENSE
MANIFEST.in
README.md
setup.py
examples/atlantis/fabfile.py
examples/atlantis/fabfile.pyc
examples/atlantis/fabfile_minimal.py
examples/atlantis/common/activate-profile.tpl
examples/atlantis/common/requirements-extra.txt
examples/atlantis/common/requirements.txt
examples/atlantis/common/rundevserver.py.tpl
examples/atlantis/common/etc/invenio-apache-vhost.conf
examples/inspire/fabfile.py
examples/inspire/common/activate-profile.tpl
examples/inspire/common/config-local.mk
examples/inspire/common/config_local.py.tpl
examples/inspire/common/requirements-extra.txt
examples/inspire/common/requirements.txt
examples/inspire/common/rundevserver.py.tpl
examples/inspire/common/etc/invenio-local.conf
examples/openaire/fabfile.py
examples/openaire/common/activate-profile.tpl
examples/openaire/common/config_local.py.tpl
examples/openaire/common/requirements-extra.txt
examples/openaire/common/requirements.txt
examples/openaire/common/rundevserver.py.tpl
examples/openaire/common/etc/invenio-local.conf
examples/openaire/int/etc/invenio-local.conf
examples/simple/fabfile.py
src/invenio_fabric.egg-info/PKG-INFO
src/invenio_fabric.egg-info/SOURCES.txt
src/invenio_fabric.egg-info/dependency_links.txt
src/invenio_fabric.egg-info/not-zip-safe
src/invenio_fabric.egg-info/requires.txt
src/invenio_fabric.egg-info/top_level.txt
src/inveniofab/__init__.py
src/inveniofab/apache.py
src/inveniofab/api.py
src/inveniofab/compound.py
src/inveniofab/devserver.py
src/inveniofab/env.py
src/inveniofab/git.py
src/inveniofab/inspire.py
src/inveniofab/invenio.py
src/inveniofab/mysql.py
src/inveniofab/test.py
src/inveniofab/utils.py
src/inveniofab/venv.py