Metadata-Version: 1.0
Name: invenio-fabric
Version: 0.2.8
Summary: Fabric tasks for working with Invenio repository software
Home-page: https://github.com/lnielsen-cern/invenio-fabric
Author: CERN
Author-email: info@invenio-software.org
License: GPL
Keywords: invenio fabric CERN
Platform: UNKNOWN
